{
  "pools": [
    {
      "name": "EnchantedBooks",
      "rolls": {
        "min": 1,
        "max": 1
      },
      "entries": [
        {
          "_name": "sharpness7",
          "type": "minecraft:item",
          "weight": 2,
          "name": "minecraft:enchanted_book",
          "functions": [
            {
              "function": "minecraft:set_count",
              "count": {
                "min": 1,
                "max": 1
              }
            },
            {
              "function": "set_nbt",
              "tag": "{StoredEnchantments:[{id:sharpness,lvl:7}]}"
            }
          ]
        },
        {
          "_name": "sharpness8",
          "type": "minecraft:item",
          "weight": 1,
          "name": "minecraft:enchanted_book",
          "functions": [
            {
              "function": "minecraft:set_count",
              "count": {
                "min": 1,
                "max": 1
              }
            },
            {
              "function": "set_nbt",
              "tag": "{StoredEnchantments:[{id:sharpness,lvl:8}]}"
            }
          ]
        },
        {
          "_name": "protection5",
          "type": "minecraft:item",
          "weight": 2,
          "name": "minecraft:enchanted_book",
          "functions": [
            {
              "function": "minecraft:set_count",
              "count": {
                "min": 1,
                "max": 1
              }
            },
            {
              "function": "set_nbt",
              "tag": "{StoredEnchantments:[{id:protection,lvl:5}]}"
            }
          ]
        },
        {
          "_name": "smite7",
          "type": "minecraft:item",
          "weight": 2,
          "name": "minecraft:enchanted_book",
          "functions": [
            {
              "function": "minecraft:set_count",
              "count": {
                "min": 1,
                "max": 1
              }
            },
            {
              "function": "set_nbt",
              "tag": "{StoredEnchantments:[{id:smite,lvl:7}]}"
            }
          ]
        },
        {
          "_name": "smite8",
          "type": "minecraft:item",
          "weight": 1,
          "name": "minecraft:enchanted_book",
          "functions": [
            {
              "function": "minecraft:set_count",
              "count": {
                "min": 1,
                "max": 1
              }
            },
            {
              "function": "set_nbt",
              "tag": "{StoredEnchantments:[{id:smite,lvl:8}]}"
            }
          ]
        },
        {
          "_name": "unbreaking5",
          "type": "minecraft:item",
          "weight": 4,
          "name": "minecraft:enchanted_book",
          "functions": [
            {
              "function": "minecraft:set_count",
              "count": {
                "min": 1,
                "max": 1
              }
            },
            {
              "function": "set_nbt",
              "tag": "{StoredEnchantments:[{id:unbreaking,lvl:5}]}"
            }
          ]
        },
        {
          "_name": "unbreaking6",
          "type": "minecraft:item",
          "weight": 2,
          "name": "minecraft:enchanted_book",
          "functions": [
            {
              "function": "minecraft:set_count",
              "count": {
                "min": 1,
                "max": 1
              }
            },
            {
              "function": "set_nbt",
              "tag": "{StoredEnchantments:[{id:unbreaking,lvl:6}]}"
            }
          ]
        },
        {
          "_name": "unbreaking7",
          "type": "minecraft:item",
          "weight": 1,
          "name": "minecraft:enchanted_book",
          "functions": [
            {
              "function": "minecraft:set_count",
              "count": {
                "min": 1,
                "max": 1
              }
            },
            {
              "function": "set_nbt",
              "tag": "{StoredEnchantments:[{id:unbreaking,lvl:7}]}"
            }
          ]
        },
        {
          "_name": "fortune5",
          "type": "minecraft:item",
          "weight": 2,
          "name": "minecraft:enchanted_book",
          "functions": [
            {
              "function": "minecraft:set_count",
              "count": {
                "min": 1,
                "max": 1
              }
            },
            {
              "function": "set_nbt",
              "tag": "{StoredEnchantments:[{id:fortune,lvl:5}]}"
            }
          ]
        },
        {
          "_name": "fortune6",
          "type": "minecraft:item",
          "weight": 1,
          "name": "minecraft:enchanted_book",
          "functions": [
            {
              "function": "minecraft:set_count",
              "count": {
                "min": 1,
                "max": 1
              }
            },
            {
              "function": "set_nbt",
              "tag": "{StoredEnchantments:[{id:fortune,lvl:6}]}"
            }
          ]
        },
        {
          "_name": "looting7",
          "type": "minecraft:item",
          "weight": 4,
          "name": "minecraft:enchanted_book",
          "functions": [
            {
              "function": "minecraft:set_count",
              "count": {
                "min": 1,
                "max": 1
              }
            },
            {
              "function": "set_nbt",
              "tag": "{StoredEnchantments:[{id:looting,lvl:7}]}"
            }
          ]
        },
        {
          "_name": "looting8",
          "type": "minecraft:item",
          "weight": 2,
          "name": "minecraft:enchanted_book",
          "functions": [
            {
              "function": "minecraft:set_count",
              "count": {
                "min": 1,
                "max": 1
              }
            },
            {
              "function": "set_nbt",
              "tag": "{StoredEnchantments:[{id:looting,lvl:8}]}"
            }
          ]
        },
        {
          "_name": "featherfalling5",
          "type": "minecraft:item",
          "weight": 2,
          "name": "minecraft:enchanted_book",
          "functions": [
            {
              "function": "minecraft:set_count",
              "count": {
                "min": 1,
                "max": 1
              }
            },
            {
              "function": "set_nbt",
              "tag": "{StoredEnchantments:[{id:feather_falling,lvl:5}]}"
            }
          ]
        }
      ]
    }
  ]
}